Metadata-Version: 1.0
Name: worch-g4lbne
Version: 0.0.2
Summary: Worch/waf tools and features for building G4LBNE.
Home-page: http://github.com/brettviren/worch-g4lbne
Author: Brett Viren
Author-email: brett.viren@gmail.com
License: GPLv2
Platform: UNKNOWN
